murasame-0.1.0-py3.9-nspkg.pth
murasame/constants.py
murasame/version.py
murasame/api/__init__.py
murasame/api/applicationapi.py
murasame/api/configurationapi.py
murasame/api/eventapi.py
murasame/api/loggingapi.py
murasame/api/vfsapi.py
murasame/application/__init__.py
murasame/application/application.py
murasame/application/applicationreturncodes.py
murasame/application/applicationtypes.py
murasame/application/businesslogic.py
murasame/configuration/__init__.py
murasame/configuration/configuration.py
murasame/configuration/configurationattribute.py
murasame/configuration/configurationbackend.py
murasame/configuration/configurationbackends.py
murasame/configuration/configurationgroup.py
murasame/configuration/configurationlist.py
murasame/configuration/configurationsource.py
murasame/configuration/dictionarybackend.py
murasame/configuration/vfsconfigurationsource.py
murasame/debug/__init__.py
murasame/debug/decorators.py
murasame/event/__init__.py
murasame/event/event.py
murasame/exceptions/__init__.py
murasame/exceptions/accessviolationerror.py
murasame/exceptions/alreadyexistserror.py
murasame/exceptions/alreadyregisterederror.py
murasame/exceptions/databaseoperationerror.py
murasame/exceptions/errorcodes.py
murasame/exceptions/exception.py
murasame/exceptions/installationfailederror.py
murasame/exceptions/invalidinputerror.py
murasame/exceptions/invalidlicensekeyerror.py
murasame/exceptions/missingrequirementerror.py
murasame/exceptions/notregisterederror.py
murasame/exceptions/uncaughtexceptionerror.py
murasame/licensing/__init__.py
murasame/licensing/licensedescriptor.py
murasame/licensing/licensefile.py
murasame/licensing/licensegenerator.py
murasame/licensing/licensetypes.py
murasame/licensing/licensevalidator.py
murasame/localization/__init__.py
murasame/localization/localizer.py
murasame/log/__init__.py
murasame/log/consolelogtarget.py
murasame/log/defaultlogconfig.py
murasame/log/filelogtarget.py
murasame/log/logchannel.py
murasame/log/logentry.py
murasame-0.1.0.dist-info/LICENSE
murasame-0.1.0.dist-info/METADATA
murasame-0.1.0.dist-info/WHEEL
murasame-0.1.0.dist-info/namespace_packages.txt
murasame-0.1.0.dist-info/top_level.txt
murasame-0.1.0.dist-info/RECORD
