Metadata-Version: 2.1
Name: murasame
Version: 0.1.0
Summary: Python application development framework used by Suisei Entertainment.
Home-page: https://github.com/suisei-entertainment/murasame
Author: Suisei Entertainment
Author-email: info@suiseientertainment.com
License: UNKNOWN
Download-URL: https://github.com/suisei-entertainment/murasame/archive/${source_archive}
Keywords: MMO,AWS,online game,virtual world
Platform: UNKNOWN
Classifier: Programming Language :: Python :: 3.9
Classifier: Development Status :: 2 - Pre-Alpha
Classifier: Intended Audience :: Developers
Classifier: Intended Audience :: Information Technology
Classifier: License :: OSI Approved :: Apache Software License
Classifier: Operating System :: POSIX :: Linux
Classifier: Topic :: Games/Entertainment
Classifier: Topic :: Software Development :: Libraries
Classifier: Topic :: Software Development :: Libraries :: Python Modules
Requires-Python: >=3.9
Requires-Dist: py-cpuinfo (>=4.0.0)
Requires-Dist: psutil (>=5.4.8)
Requires-Dist: netifaces (>=0.10.7)
Requires-Dist: distro (>=1.3.0)
Requires-Dist: wget (>=3.2)
Requires-Dist: urllib3 (>=1.26.4)
Requires-Dist: requests (>=2.23.0)
Requires-Dist: aiohttp (>=3.7.4)
Requires-Dist: geoip2 (>=4.2.0)
Requires-Dist: cryptography (>=3.4.6)
Requires-Dist: bcrypt (>=3.1.7)
Requires-Dist: protobuf (>=3.11.2)
Requires-Dist: googletrans (>=3.1.0a0)
Requires-Dist: termcolor (>=1.1.0)
Requires-Dist: coloredlogs (>=10.0)
Requires-Dist: flask (>=1.1.1)
Requires-Dist: Flask-Session (>=0.3.1)
Requires-Dist: sentry-sdk
Requires-Dist: influxdb (>=5.3.0)
Requires-Dist: redis (>=3.5.2)
Requires-Dist: pyyaml (>=5.4.1)
Requires-Dist: python-magic
